erwin/__init__.py
erwin/__main__.py
erwin/cli.py
erwin/b0_map/__init__.py
erwin/b0_map/double_echo.py
erwin/b1_map/__init__.py
erwin/b1_map/afi.py
erwin/cbf/__init__.py
erwin/cbf/asl_bold_to_asl.py
erwin/cbf/pasl.py
erwin/diffusion/__init__.py
erwin/diffusion/b_zero.py
erwin/diffusion/bruker_to_mif.py
erwin/diffusion/fod_segmentation.py
erwin/diffusion/mask.py
erwin/diffusion/mean_response.py
erwin/diffusion/mif_io.py
erwin/diffusion/multi_tissue_normalization.py
erwin/diffusion/noddi.py
erwin/diffusion/noddi_responses.py
erwin/diffusion/preprocessing.py
erwin/diffusion/siemens_to_mif.py
erwin/diffusion/sift2.py
erwin/diffusion/spherical_deconvolution_response.py
erwin/diffusion/spherical_harmonics.py
erwin/diffusion/tensor.py
erwin/diffusion/tensor_metric.py
erwin/diffusion/tractography.py
erwin/meta_data/__init__.py
erwin/meta_data/get.py
erwin/meta_data/siemens.py
erwin/misc/__init__.py
erwin/misc/time_to_rate.py
erwin/moco/__init__.py
erwin/moco/ants.py
erwin/moco/apply_ants.py
erwin/mt_map/__init__.py
erwin/mt_map/mpf.cpython-311-x86_64-linux-gnu.so
erwin/mt_map/mtr.py
erwin/mt_map/single_point.py
erwin/qsm/__init__.py
erwin/qsm/background_field_removal.py
erwin/qsm/medi_l1.py
erwin/qsm/r2_star.py
erwin/qsm/total_field.py
erwin/qsm/ventricles_mask.py
erwin/segmentation/__init__.py
erwin/segmentation/bet.py
erwin/t1_map/__init__.py
erwin/t1_map/vfa.py
erwin/t2_map/__init__.py
erwin/t2_map/bssfp.py
erwin/t2_map/pssfp.py
erwin-1.3.0.dist-info/LICENSE
erwin-1.3.0.dist-info/METADATA
erwin-1.3.0.dist-info/WHEEL
erwin-1.3.0.dist-info/entry_points.txt
erwin-1.3.0.dist-info/top_level.txt
erwin-1.3.0.dist-info/RECORD
