Metadata-Version: 2.1
Name: erwin
Version: 1.3.0
Summary: Toolbox to generate quantitative maps from MRI images
Home-page: https://github.com/lamyj/erwin
Author: J. Lamy, M. Mondino, P. Loureiro de Sousa
Maintainer: Julien Lamy
Maintainer-email: lamy@unistra.fr
License: MIT
Keywords: MRI,quantitative,field mapping,B0,B1,CBF,cerebral blood flow,ASL,arterial spin labeling,pASL,diffusion,DTI,diffusion tensor,spherical harmonics,MT,magnetization transfer,relaxometry,T1,VFA,T2,bSSFP
Classifier: Development Status :: 5 - Production/Stable
Classifier: Environment :: Console
Classifier: Intended Audience :: Healthcare Industry
Classifier: Intended Audience :: Science/Research
Classifier: License :: OSI Approved :: MIT License
Classifier: Programming Language :: Python :: 3
Classifier: Topic :: Scientific/Engineering :: Image Processing
Classifier: Topic :: Scientific/Engineering :: Medical Science Apps.
Classifier: Topic :: Scientific/Engineering :: Physics
Requires-Python: >=3.7
License-File: LICENSE
Requires-Dist: cython
Requires-Dist: docutils
Requires-Dist: doit
Requires-Dist: meg
Requires-Dist: nibabel
Requires-Dist: numpy
Requires-Dist: pydicom
Requires-Dist: scipy
Requires-Dist: sphinx
Requires-Dist: spire-pipeline (>=1.1.1)
